openspeech/__init__.py
openspeech/metrics.py
openspeech/utils.py
openspeech/criterion/__init__.py
openspeech/criterion/cross_entropy/__init__.py
openspeech/criterion/cross_entropy/configuration.py
openspeech/criterion/cross_entropy/cross_entropy.py
openspeech/criterion/ctc/__init__.py
openspeech/criterion/ctc/configuration.py
openspeech/criterion/ctc/ctc.py
openspeech/criterion/joint_ctc_cross_entropy/__init__.py
openspeech/criterion/joint_ctc_cross_entropy/configuration.py
openspeech/criterion/joint_ctc_cross_entropy/joint_ctc_cross_entropy.py
openspeech/criterion/label_smoothed_cross_entropy/__init__.py
openspeech/criterion/label_smoothed_cross_entropy/configuration.py
openspeech/criterion/label_smoothed_cross_entropy/label_smoothed_cross_entropy.py
openspeech/criterion/transducer/__init__.py
openspeech/criterion/transducer/configuration.py
openspeech/criterion/transducer/transducer.py
openspeech/data/__init__.py
openspeech/data/data_loader.py
openspeech/data/dataset.py
openspeech/data/audio/__init__.py
openspeech/data/audio/augment.py
openspeech/data/audio/load.py
openspeech/data/audio/filter_bank/__init__.py
openspeech/data/audio/filter_bank/configuration.py
openspeech/data/audio/filter_bank/filter_bank.py
openspeech/data/audio/melspectrogram/__init__.py
openspeech/data/audio/melspectrogram/configuration.py
openspeech/data/audio/melspectrogram/melspectrogram.py
openspeech/data/audio/mfcc/__init__.py
openspeech/data/audio/mfcc/configuration.py
openspeech/data/audio/mfcc/mfcc.py
openspeech/data/audio/spectrogram/__init__.py
openspeech/data/audio/spectrogram/configuration.py
openspeech/data/audio/spectrogram/spectrogram.py
openspeech/dataclass/__init__.py
openspeech/dataclass/configurations.py
openspeech/dataclass/initialize.py
openspeech/datasets/__init__.py
openspeech/datasets/aishell/__init__.py
openspeech/datasets/aishell/lit_data_module.py
openspeech/datasets/aishell/preprocess.py
openspeech/datasets/ksponspeech/__init__.py
openspeechs-0.1.dist-info/LICENSE
openspeechs-0.1.dist-info/LICENSE.3rd_party_library
openspeechs-0.1.dist-info/METADATA
openspeechs-0.1.dist-info/WHEEL
openspeechs-0.1.dist-info/top_level.txt
openspeechs-0.1.dist-info/RECORD
