Metadata-Version: 2.1
Name: openspeechs
Version: 0.1
Summary: Open-Source Toolkit for End-to-End Automatic Speech Recognition
Home-page: https://github.com/sooftware/openspeech
Author: Kim, Soohwan and Ha, Sangchun and Cho, Soyoung
Author-email: sh951011@gmail.com, seomk9896@naver.com, soyoung.cho@kaist.ac.kr
License: UNKNOWN
Download-URL: https://github.com/sooftware/openspeech/releases/tag/v0.1.zip
Keywords: openspeech,asr,speech_recognition,pytorch-lightning,hydra
Platform: UNKNOWN
Requires-Python: >=3.7
Requires-Dist: torch (>=1.4.0)
Requires-Dist: python-Levenshtein
Requires-Dist: numpy
Requires-Dist: pandas
Requires-Dist: astropy
Requires-Dist: sentencepiece
Requires-Dist: pytorch-lightning
Requires-Dist: hydra-core
Requires-Dist: wget
Requires-Dist: wandb
